{"page":"resources","videoHero":{"videoUrls":["https://oakwoodsys.com/wp-content/uploads/2026/02/Case_Studies.mp4"],"title":"Turn Data and AI Into Real Business Outcomes","description":"Explore case studies and insights from projects built on Azure that solve real problems.","ctaPrimary":{"text":"Watch the video","link":"/","backgroundColor":"#1A63C9"},"ctaSecondary":{"text":"View Resources","link":"/resources","borderColor":"#ffffff"}},"hero":{"title":"Discover Our Impact Through Realized Projects","description":"Real solutions built on Azure AI that solve real problems, not theoretical ones.","backgroundImage":"/assets/resources/hero-background.jpg","ctaPrimary":{"text":"Schedule a Consultation","link":"/contact-us"},"ctaSecondary":{"text":"View Resources","link":"/resources"}},"featuredCaseStudy":{"label":"FEATURED CASE STUDY","readMoreText":"Read More"},"featuredCaseStudySlugs":["secure-azure-research-environment-architecture","enterprise-reporting-and-data-roadmap-development"],"filters":[{"displayCategory":"All","value":"All"},{"displayCategory":"High-Performance Computing (HPC)","value":"high-performance-computing-hpc"},{"displayCategory":"Data & AI Solutions","value":"data-ai-solutions"},{"displayCategory":"Cloud & Infrastructure","value":"cloud-infrastructure"},{"displayCategory":"Application Innovation","value":"application-innovation"},{"displayCategory":"Modern Work","value":"modern-work"},{"displayCategory":"Managed Services","value":"managed-services"},{"displayCategory":"Microsoft Licensing","value":"microsoft-licensing"},{"displayCategory":"Manufacturing","value":"manufacturing"},{"displayCategory":"Healthcare","value":"healthcare"},{"displayCategory":"Financial Services","value":"financial-services"},{"displayCategory":"Retail","value":"retail"},{"displayCategory":"Education/Public Sector","value":"education-public-sector"},{"displayCategory":"Electronic Design Automation (EDA)","value":"electronic-design-automation-eda"},{"displayCategory":"Other","value":"other"}],"filterAndSearch":{"searchPlaceholder":"Search","emptyStateMessage":"No resources found matching your criteria."},"resourcesGrid":{"loadMoreText":"Load More","readMoreText":"Read More"},"ctaSection":{"title":"Let's move your vision forward","description":"Connect with a team committed to helping you modernize, innovate, and achieve meaningful results.","ctaPrimary":{"text":"Talk to an expert","link":"/contact-us"},"ctaSecondary":{"text":"Schedule a call","link":"/contact-us"}}}
